Mahitha36_pypi/__init__.py
Mahitha36_pypi/core.py
mahitha36_pypi-0.1.0.dist-info/licenses/LICENSE
mahitha36_pypi-0.1.0.dist-info/METADATA
mahitha36_pypi-0.1.0.dist-info/WHEEL
mahitha36_pypi-0.1.0.dist-info/top_level.txt
mahitha36_pypi-0.1.0.dist-info/RECORD
