Metadata-Version: 2.4
Name: mahitha36_pypi
Version: 0.1.0
Summary: A Python package for data analysis and visualization using Pandas, NumPy, Matplotlib, and Seaborn.
Home-page: https://github.com/mahithanadakuditi/mahitha36-pypi
Author: Mahitha Nadakuditi
Author-email: mahithanadakuditi@gmail.com
Project-URL: Bug Tracker, https://github.com/mahithanadakuditi/mahitha36-pypi/issues
Classifier: Programming Language :: Python :: 3
Classifier: License :: OSI Approved :: MIT License
Classifier: Operating System :: OS Independent
Requires-Python: >=3.6
License-File: LICENSE
Requires-Dist: pandas>=1.0
Requires-Dist: numpy>=1.18
Requires-Dist: matplotlib>=3.0
Requires-Dist: seaborn>=0.10
Dynamic: author
Dynamic: author-email
Dynamic: classifier
Dynamic: description
Dynamic: description-content-type
Dynamic: home-page
Dynamic: license-file
Dynamic: project-url
Dynamic: requires-dist
Dynamic: requires-python
Dynamic: summary
